zvi/__init__.py
zvi/display.py
zvi/hashes.py
zvi/pandas.py
zvi/plot.py
zvi/proxies.py
zvi-1.0.0.dist-info/LICENSE.txt
zvi-1.0.0.dist-info/METADATA
zvi-1.0.0.dist-info/WHEEL
zvi-1.0.0.dist-info/top_level.txt
zvi-1.0.0.dist-info/RECORD
